{
  "title": "Dynasty Urban Style | Meeting your fashion needs",
  "titleTemplate": "%s - Dynasty Urban Style",
  "description": "Meeting the fashion needs of the urban community",
  "openGraph": {
    "title": "Dynasty Urban Style | Meeting your fashion needs",
    "description": "Meeting the fashion needs of the urban community",
    "type": "website",
    "url": "https://nextjs.org/commerce",
    "site_name": "Dynasty Urban Style",
    "images": [
      {
        "url": "/card.png",
        "width": "800",
        "height": "600",
        "alt": "Dynasty Urban Style"
      }
    ]
  },
  "twitter": {
    "handle": "@dynasty_urban_style",
    "site": "@dynasty_urban_style",
    "cardType": "summary_large_image"
  }
}
